khaki/__init__.py
khaki/__main__.py
khaki/alarm.wav
khaki-0.3.2.dist-info/entry_points.txt
khaki-0.3.2.dist-info/LICENSE.md
khaki-0.3.2.dist-info/WHEEL
khaki-0.3.2.dist-info/METADATA
khaki-0.3.2.dist-info/RECORD
