Metadata-Version: 2.1
Name: khaki
Version: 0.3.2
Summary: A simple Pomodoro timer using curses (and pyglet for audio playback)
Home-page: UNKNOWN
License: MIT
Keywords: timer,productivity
Author: Tarcisio Eduardo Moreira Crocomo
Author-email: tarcisioe@pm.me
Requires-Python: >=3.4,<4.0
Classifier: License :: OSI Approved :: MIT License
Classifier: Programming Language :: Python :: 3
Classifier: Programming Language :: Python :: 3.4
Classifier: Programming Language :: Python :: 3.5
Classifier: Programming Language :: Python :: 3.6
Classifier: Programming Language :: Python :: 3.7
Requires-Dist: pyglet (>=1.3.2,<2.0.0)
